MANIFEST.in
README.rst
setup.py
cpv/__init__.py
cpv/_common.py
cpv/acf.py
cpv/comb-p
cpv/fdr.py
cpv/filter.py
cpv/hist.py
cpv/manhattan.py
cpv/peaks.py
cpv/pipeline.py
cpv/qvality.py
cpv/region_p.py
cpv/slk.py
cpv/stepsize.py
cpv/stouffer_liptak.py
cpv.egg-info/PKG-INFO
cpv.egg-info/SOURCES.txt
cpv.egg-info/dependency_links.txt
cpv.egg-info/requires.txt
cpv.egg-info/top_level.txt
cpv/tests/__init__.py
cpv/tests/test.py
cpv/tests/data/expected_acf.txt
cpv/tests/data/pvals.bed