Metadata-Version: 1.1
Name: cpv
Version: 0.48
Summary: combine p-values
Home-page: https://github.com/brentp/combined-pvalues
Author: Brent Pedersen
Author-email: bpederse@gmail.com
License: MIT
Platform: UNKNOWN
Classifier: Topic :: Scientific/Engineering :: Bio-Informatics
